natthaphon/__init__.py
natthaphon/datasets.py
natthaphon/pytorch_api.py
natthaphon/utils.py
natthaphon-1.0.0.dist-info/LICENSE
natthaphon-1.0.0.dist-info/METADATA
natthaphon-1.0.0.dist-info/WHEEL
natthaphon-1.0.0.dist-info/top_level.txt
natthaphon-1.0.0.dist-info/RECORD
