Metadata-Version: 2.1
Name: natthaphon
Version: 1.0.0
Summary: Added epoch end
Home-page: https://github.com/DableUTeeF/pytorch_api
Author: Natthaphon Hongcharoen
Author-email: palm22180@gmail.com
License: UNKNOWN
Platform: UNKNOWN
Classifier: Programming Language :: Python :: 3
Classifier: License :: OSI Approved :: MIT License
Classifier: Operating System :: OS Independent
